<?xml version="1.0" encoding="utf-8" ?>
<dwsync>
<file name="alpha.png" server="192.168.0.100//web/" local="127891401600000000" remote="130198932600000000" Dst="1" />
<file name="bug.eps" server="192.168.0.100//web/" local="130129979080000000" remote="130198932600000000" Dst="1" />
<file name="img.png" server="192.168.0.100//web/" local="127891401800000000" remote="130198932600000000" Dst="1" />
<file name="image_with_alpha.png" server="192.168.0.100//web/" local="127891400080000000" remote="130198932600000000" Dst="1" />
<file name="logo_example.gif" server="192.168.0.100//web/" local="128438335140000000" remote="130198932600000000" Dst="1" />
<file name="logo_example.jpg" server="192.168.0.100//web/" local="128438335280000000" remote="130198932600000000" Dst="1" />
<file name="logo_example.png" server="192.168.0.100//web/" local="127836746680000000" remote="130198932600000000" Dst="1" />
<file name="pelican.ai" server="192.168.0.100//web/" local="130129979080000000" remote="130198932600000000" Dst="1" />
<file name="tcpdf_cell.png" server="192.168.0.100//web/" local="129309896500000000" remote="130198932600000000" Dst="1" />
<file name="tcpdf_logo.jpg" server="192.168.0.100//web/" local="128490567020000000" remote="130198932600000000" Dst="1" />
<file name="testsvg.svg" server="192.168.0.100//web/" local="129208575340000000" remote="130198932600000000" Dst="1" />
<file name="image_demo.jpg" server="192.168.0.100//web/" local="128490642640000000" remote="130198932600000000" Dst="1" />
<file name="tcpdf_signature.png" server="192.168.0.100//web/" local="129211494700000000" remote="130198932600000000" Dst="1" />
<file name="_blank.png" server="192.168.0.100//web/" local="127836746680000000" remote="130198932600000000" Dst="1" />
<file name="tux.svg" server="192.168.0.100//web/" local="129182046100000000" remote="130198932600000000" Dst="1" />
<file name="tiger.ai" server="192.168.0.100//web/" local="130129979080000000" remote="130198932600000000" Dst="1" />
</dwsync>